crypto_tools/__init__.py
crypto_tools/analysis/__init__.py
crypto_tools/analysis/language_estimator.py
crypto_tools/data/__init__.py
crypto_tools/data/bigram_frequency_by_language.py
crypto_tools/data/frequent_short_words_by_language.py
crypto_tools/data/index_of_coincidence_by_language.py
crypto_tools/data/letter_frequency_by_language.py
crypto_tools/data/tetragram_frequency_by_language.py
crypto_tools/data/trigram_frequency_by_language.py
crypto_tools/stats/__init__.py
crypto_tools/stats/index_of_coincidence.py
crypto_tools/stats/letter_counter.py
crypto_tools/stats/letter_frequency.py
crypto_tools/stats/ngram_counter.py
crypto_tools/stats/ngram_frequency.py
crypto_tools/utils/__init__.py
crypto_tools/utils/string_utils.py
crypto_tools-1.0.14.dist-info/LICENSE
crypto_tools-1.0.14.dist-info/METADATA
crypto_tools-1.0.14.dist-info/WHEEL
crypto_tools-1.0.14.dist-info/top_level.txt
crypto_tools-1.0.14.dist-info/RECORD
