Metadata-Version: 2.1
Name: crypto-tools
Version: 1.0.14
Summary: Tools that can be used to build software for breaking "traditional" cyphers and codes.
Home-page: https://github.com/roccobarbi/crypto_tools
Author: Rocco Barbini
Author-email: roccobarbi@gmail.com
License: UNKNOWN
Download-URL: https://github.com/roccobarbi/crypto_tools/releases/tag/1.0.14
Platform: UNKNOWN
Classifier: Programming Language :: Python :: 3
Classifier: License :: OSI Approved :: MIT License
Classifier: Operating System :: OS Independent
License-File: LICENSE
